<Namespace Name="System">
  <Metadata><Meta Name="ms.openlocfilehash" Value="08535e3412a204896a9766410aaf1ac2768eb297" /><Meta Name="ms.sourcegitcommit" Value="88014e1c5440e3df4f66ef04393854d15b1fd534" /><Meta Name="ms.translationtype" Value="MT" /><Meta Name="ms.contentlocale" Value="ru-RU" /><Meta Name="ms.lasthandoff" Value="09/05/2019" /><Meta Name="ms.locfileid" Value="70633976" /></Metadata><Docs>
    <summary>Пространство имен <see cref="N:System" /> содержит фундаментальные и базовые классы, определяющие часто используемые типы значений и ссылочных данных, события и обработчики событий, интерфейсы, атрибуты и исключения обработки.</summary>
    <remarks>
      <format type="text/markdown"><![CDATA[  
  
## Remarks  
 Другие классы предоставляют службы, поддерживающие преобразование типов данных, обработку параметров методов, математику, удаленный и локальный вызов программы, управление средой приложений и контроль управляемых и неуправляемых приложений.  
  
 Чтобы получить доступ к типам <xref:System> в пространстве C# имен из кода без необходимости указывать полные `using System;` имена типов, включите оператор в начало файла исходного кода.  
  
 Чтобы получить доступ к типам <xref:System> в пространстве C++имен из кода/CLI без указания полных `using namespace System;` имен типов, включите оператор в начало файла исходного кода. Кроме того, необходимо выполнить компиляцию с параметром [/CLR](https://msdn.microsoft.com/library/fec5a8c0-40ec-484c-a213-8dec918c1d6c) .  
  
 ]]></format>
    </remarks>
  </Docs>
</Namespace>