<Namespace Name="System.Data.Common">
  <Metadata><Meta Name="ms.openlocfilehash" Value="48017f6eae1eb7edc1508f8ab37024e1dfe33804" /><Meta Name="ms.sourcegitcommit" Value="88014e1c5440e3df4f66ef04393854d15b1fd534" /><Meta Name="ms.translationtype" Value="MT" /><Meta Name="ms.contentlocale" Value="ru-RU" /><Meta Name="ms.lasthandoff" Value="09/05/2019" /><Meta Name="ms.locfileid" Value="70522465" /></Metadata><Docs>
    <summary>Пространство имен <see cref="N:System.Data.Common" /> содержит классы, совместно используемые поставщиками данных .NET Framework.</summary>
    <remarks>
      <format type="text/markdown"><![CDATA[  
  
## Remarks  
 Поставщик данных .NET Framework описывает коллекцию классов, которые используются для доступа к источнику данных, например к базе данных, в управляемом пространстве. Поддерживаются следующие поставщики данных: .NET Framework Data Provider для ODBC, .NET Framework Data Provider для OLEDB, .NET Framework Data Provider для Oracle и .NET Framework Data Provider для SQL Server. Классы в пространстве имен <xref:System.Data.Common> предназначены для предоставления разработчикам возможности писать код ADO.NET, который будет работать со всеми поставщиками данных .NET Framework.  
  
 Основные сведения о том, как использовать это пространство имен при программировании с помощью the.NET Framework, см. [в разделе Написание независимого от поставщика кода с помощью ADO.NET](https://msdn.microsoft.com/library/6db08c56-eafe-4d2f-986b-6e4d8522cb9e).  
  
 ]]></format>
    </remarks>
  </Docs>
</Namespace>