<Namespace Name="System.Windows.Markup">
  <Metadata><Meta Name="ms.openlocfilehash" Value="0c41cb4e90e570874b89f9e31aab58f4bde3d83d" /><Meta Name="ms.sourcegitcommit" Value="88014e1c5440e3df4f66ef04393854d15b1fd534" /><Meta Name="ms.translationtype" Value="MT" /><Meta Name="ms.contentlocale" Value="ru-RU" /><Meta Name="ms.lasthandoff" Value="09/05/2019" /><Meta Name="ms.locfileid" Value="70596925" /></Metadata><Docs>
    <summary><span data-ttu-id="bc55b-101">Предоставляет типы, поддерживающие XAML.</span><span class="sxs-lookup"><span data-stu-id="bc55b-101">Provides types to support XAML.</span></span> <span data-ttu-id="bc55b-102">Некоторые из этих типов расположены в сборках WPF и относятся к сценариям WPF, в которых используется XAML.</span><span class="sxs-lookup"><span data-stu-id="bc55b-102">Some of these types are located in WPF assemblies and are specific to WPF scenarios that involve XAML.</span></span> <span data-ttu-id="bc55b-103">Другие типы этого пространства имен обеспечивают общую поддержку служб XAML платформы .NET Framework, и для них не требуются ссылки на сборки WPF.</span><span class="sxs-lookup"><span data-stu-id="bc55b-103">Other types in this namespace provide support for .NET Framework XAML Services in general, and do not require referencing WPF assemblies.</span></span></summary>
    <remarks>To be added.</remarks>
  </Docs>
</Namespace>